robotic_arm_env/__init__.py
robotic_arm_env/env.py
robotic_arm_env-0.3.dist-info/METADATA
robotic_arm_env-0.3.dist-info/WHEEL
robotic_arm_env-0.3.dist-info/top_level.txt
robotic_arm_env-0.3.dist-info/RECORD
