Metadata-Version: 2.2
Name: robotic_arm_env
Version: 0.3
Summary: A robotic arm environment for reinforcement learning
Home-page: https://github.com/yourusername/robotic_arm_env
Author: Your Name
Author-email: your.email@example.com
Classifier: Programming Language :: Python :: 3
Classifier: License :: OSI Approved :: MIT License
Classifier: Operating System :: OS Independent
Requires-Python: >=3.6
Requires-Dist: gym
Requires-Dist: pybullet
Requires-Dist: numpy
Requires-Dist: stable-baselines3
Requires-Dist: opencv-python
Dynamic: author
Dynamic: author-email
Dynamic: classifier
Dynamic: home-page
Dynamic: requires-dist
Dynamic: requires-python
Dynamic: summary
